install.json
jupyterlab-visualpython/_version.py
lib/VpPanel.js
lib/index.js
lib/visualpython/__init__.py
lib/visualpython/visualpython.js
lib/visualpython/visualpython.yaml
lib/visualpython/bin/__init__.py
lib/visualpython/bin/visualpy
lib/visualpython/bin/visualpy.bat
lib/visualpython/css/__init__.py
lib/visualpython/css/boardFrame.css
lib/visualpython/css/mainFrame.css
lib/visualpython/css/menuFrame.css
lib/visualpython/css/root.css
lib/visualpython/css/component/__init__.py
lib/visualpython/css/component/alertModal.css
lib/visualpython/css/component/dataSelector.css
lib/visualpython/css/component/fileNavigation.css
lib/visualpython/css/component/infoModal.css
lib/visualpython/css/component/innerFuncViewer.css
lib/visualpython/css/component/instanceEditor.css
lib/visualpython/css/component/loadingSpinner.css
lib/visualpython/css/component/modal.css
lib/visualpython/css/component/multiSelector.css
lib/visualpython/css/component/packageManager.css
lib/visualpython/css/component/popupComponent.css
lib/visualpython/css/component/successMessage.css
lib/visualpython/css/m_apps/__init__.py
lib/visualpython/css/m_apps/bind.css
lib/visualpython/css/m_apps/file.css
lib/visualpython/css/m_apps/frame.css
lib/visualpython/css/m_apps/groupby.css
lib/visualpython/css/m_apps/import.css
lib/visualpython/css/m_apps/information.css
lib/visualpython/css/m_apps/instance.css
lib/visualpython/css/m_apps/markdown.css
lib/visualpython/css/m_apps/pdf.css
lib/visualpython/css/m_apps/profiling.css
lib/visualpython/css/m_apps/reshape.css
lib/visualpython/css/m_apps/snippets.css
lib/visualpython/css/m_apps/subset.css
lib/visualpython/css/m_apps/sweetviz.css
lib/visualpython/css/m_apps/variable.css
lib/visualpython/css/m_library/__init__.py
lib/visualpython/css/m_library/libraryComponent.css
lib/visualpython/css/m_library/numpyComponent.css
lib/visualpython/css/m_logic/__init__.py
lib/visualpython/css/m_logic/for.css
lib/visualpython/css/m_ml/__init__.py
jupyterlab_visualpython-3.0.2.dist-info/METADATA
jupyterlab_visualpython-3.0.2.dist-info/WHEEL
jupyterlab_visualpython-3.0.2.dist-info/licenses/LICENSE
jupyterlab_visualpython-3.0.2.dist-info/RECORD
