Metadata-Version: 2.3
Name: jupyterlab-visualpython
Version: 3.0.2
Dynamic: Keywords
Summary: GUI-based Python code generator for Jupyter Lab as an extension
Project-URL: Homepage, https://github.com/visualpython/visualpython
Project-URL: Bug Tracker, https://github.com/visualpython/visualpython/issues
Project-URL: Repository, https://github.com/visualpython/visualpython.git
Author-email: BlackLogic <blacklogic.dev@gmail.com>
License: 
License-File: LICENSE
Classifier: Framework :: Jupyter
Classifier: Framework :: Jupyter :: JupyterLab
Classifier: Framework :: Jupyter :: JupyterLab :: 4
Classifier: Framework :: Jupyter :: JupyterLab :: Extensions
Classifier: Framework :: Jupyter :: JupyterLab :: Extensions :: Prebuilt
Classifier: License :: OSI Approved :: GNU General Public License v3 (GPLv3)
Classifier: Programming Language :: Python
Classifier: Programming Language :: Python :: 3
Classifier: Programming Language :: Python :: 3.8
Classifier: Programming Language :: Python :: 3.9
Classifier: Programming Language :: Python :: 3.10
Classifier: Programming Language :: Python :: 3.11
Requires-Python: >=3.8
